.DS_Store
pytaxize/__init__.py
pytaxize/col.py
pytaxize/gbif_utils.py
pytaxize/gni.py
pytaxize/gnr.py
pytaxize/ids.py
pytaxize/itis.py
pytaxize/itis_extra.py
pytaxize/refactor.py
pytaxize/sci2comm.py
pytaxize/scicomm.py
pytaxize/tax.py
pytaxize/taxo.py
pytaxize/tnrs.py
pytaxize/ubio.py
pytaxize/utils.py
pytaxize/col/__init__.py
pytaxize/col/col.py
pytaxize/data/apg_families.csv
pytaxize/data/apg_orders.csv
pytaxize/data/plantGenusNames.csv
pytaxize/data/plantNames.csv
pytaxize/data/rank_ref.csv
pytaxize/gbif/__init__.py
pytaxize/gbif/gbif_utils.py
pytaxize/gbif/parse.py
pytaxize/gn/__init__.py
pytaxize/gn/gni.py
pytaxize/gn/gnr.py
pytaxize/ids/__init__.py
pytaxize/ids/ids.py
pytaxize/itis/__init__.py
pytaxize/itis/itis.py
pytaxize/itis/itis_extra.py
pytaxize/ncbi/__init__.py
pytaxize/ncbi/ncbi.py
test/__init__.py
test/test_Ids.py
test/test_col.py
test/test_gni.py
test/test_gnr.py
test/test_itis.py
test/test_scicomm.py
test/test_taxosaurus.py
pytaxize-0.7.0.dist-info/LICENSE
pytaxize-0.7.0.dist-info/METADATA
pytaxize-0.7.0.dist-info/WHEEL
pytaxize-0.7.0.dist-info/pbr.json
pytaxize-0.7.0.dist-info/top_level.txt
pytaxize-0.7.0.dist-info/RECORD
