Metadata-Version: 2.1
Name: pytaxize
Version: 0.7.0
Summary: Taxonomic toolbelt for Python
Home-page: https://github.com/sckott/pytaxize
Author: Scott Chamberlain
Author-email: myrmecocystus@gmail.com
License: MIT
Platform: UNKNOWN
Classifier: Development Status :: 3 - Alpha
Classifier: Intended Audience :: Science/Research
Classifier: Intended Audience :: Developers
Classifier: Topic :: Scientific/Engineering :: Bio-Informatics
Classifier: Natural Language :: English
Classifier: License :: OSI Approved :: MIT License
Classifier: Programming Language :: Python
Classifier: Programming Language :: Python :: 3
Requires-Dist: requests
Requires-Dist: lxml
Requires-Dist: multipledispatch
Provides-Extra: dataframe
Requires-Dist: pandas ; extra == 'dataframe'
Provides-Extra: test
Requires-Dist: vcrpy ; extra == 'test'
Requires-Dist: vcrpy-unittest ; extra == 'test'
